gridly-0.6.1.dist-info/METADATA
gridly-0.6.1.dist-info/RECORD
gridly-0.6.1.dist-info/WHEEL
gridly-0.6.1.dist-info/top_level.txt
gridly-0.6.1.dist-info/DESCRIPTION.rst
gridly-0.6.1.dist-info/metadata.json
gridly/__init__.py
gridly/location.py
gridly/direction.py
gridly/grid/base.py
gridly/grid/composite.py
gridly/grid/dense.py
gridly/grid/__init__.py
gridly/grid/sparse.py
